shrinemaiden/__init__.py
shrinemaiden/augmentor.py
shrinemaiden/charmap.py
shrinemaiden/train.py
shrinemaiden/transcript.py
shrinemaiden/transcript_class.py
shrinemaiden/util.py
shrinemaiden/utils.py
shrinemaiden-0.3.2.dist-info/LICENSE
shrinemaiden-0.3.2.dist-info/METADATA
shrinemaiden-0.3.2.dist-info/WHEEL
shrinemaiden-0.3.2.dist-info/top_level.txt
shrinemaiden-0.3.2.dist-info/RECORD
