Metadata-Version: 2.1
Name: shrinemaiden
Version: 0.3.2
Summary: An auxiliary library to help process data for ML/DL purposes
Home-page: https://github.com/VirtuousCrane/shrinemaiden.git
Author: VirtuousCrane
License: MIT
Platform: UNKNOWN
Classifier: License :: OSI Approved :: MIT License
Classifier: Programming Language :: Python :: 3
Classifier: Programming Language :: Python :: 3.7
Requires-Dist: librosa
Requires-Dist: tensorflow
Requires-Dist: numpy
Requires-Dist: keras
Requires-Dist: scikit-learn
Requires-Dist: Pillow
